{
  "$schema": "./dataSchema.json",
  "quiz": [
    {
      "language": "malayalam",
      "title": "രോഗ സാധ്യതയുണ്ടോ? അങ്ങിനെയുള്ളവരെ പരിചയമുണ്ടോ?",
      "description": "നിങ്ങൾ 60 വയസ്സിനു മുകളിലോ, രോഗമുള്ളയാളോ (രക്തസമ്മർദ്ദം, പ്രമേഹം, ക്യാൻസർ, ഹൃദ്രോഗം തുടങ്ങിയവ...), അല്ലെങ്കിൽ അവരെ പരിചയമുള്ളവരോ ആണോ? എങ്കിൽ താഴെയുള്ള ബട്ടൺ അമർത്തി രജിസ്റ്റർ ചെയ്യുക",
      "path": "citizen_ml",
      "buttonText": "രജിസ്റ്റർ ചെയ്യുക",
      "successMessage": "നന്ദി. Thank You.",
      "readMore": "/",
      "questions": [
        {
          "title": "ആരെ പറ്റിയുള്ള വിവരങ്ങള്‍ ആണ് നല്‍കുന്നത് ?",
          "qno":0,
          "description": "add description for question",
          "hint": "",
          "answers": [
            {
              "option": "സ്വയം / Yourself",
              "title": "",
              "description": [],
              "nextQues":1,
              "correctAnswer": true
            },
            {
              "option": "മറ്റൊരാളെ പറ്റി / Someone elseല",
              "title": "",
              "description": [],
              "nextQues":2,
              "correctAnswer": true
            }
          ]
        },
        {
          "title": "റിപ്പോര്‍ട്ട്‌ ചെയുന്ന വ്യക്തിയുടെ പേര്",
          "qno":1,
          "description": "add description for question",
          "hint": "",
          "mode": "text",
          "nextQues":5,
          "answers": []
        },
        {
          "title": "നിങ്ങൾ റിപ്പോർട്ടുചെയ്യുന്ന വ്യക്തിയുടെ പേര്",
          "qno":2,
          "description": "add description for question",
          "hint": "",
          "mode": "text",
          "nextQues":3,
          "answers": []
        },
        {
          "title": "റിപ്പോര്‍ട്ട്‌ ചെയ്യപ്പെട്ട വ്യക്തിയും നിങ്ങളും തമ്മിലുള്ള ബന്ധം",
          "qno":3,
          "description": "add description for question",
          "hint": "",
          "mode": "text",
          "nextQues":4,
          "answers": []
        },
        {
          "title": "റിപ്പോര്‍ട്ട് ചെയ്യപ്പെട്ട വ്യക്തിയെ ബന്ധപെടാനുള്ള ഫോണ്‍ നമ്പര്‍",
          "qno":4,
          "description": "add description for question",
          "hint": "",
          "mode": "text",
          "nextQues":5,
          "answers": []
        },
        {
          "title": "എന്തിനെ കുറിച്ച് ആണ്  റിപ്പോര്‍ട്ട് ചെയ്യാനുള്ളത്",
          "qno":5,
          "description": "add description for question",
          "hint": "",
          "answers": [
            {
              "option": "രോഗ ലക്ഷണങ്ങള്‍ / Symptoms",
              "title": "",
              "description": [],
              "nextQues":6,
              "correctAnswer": true
            },
            {
              "option": "60 വയസ്സിനു മുകളിൽ / Over 60 year age",
              "title": "",
              "description": [],
              "nextQues":7,
              "correctAnswer": true
            },
            {
              "option": "മറ്റ് രോഗങ്ങള്‍ / Co-morbidities",
              "title": "",
              "description": [],
              "nextQues":7,
              "correctAnswer": true
            },
            {
              "option": "വീട്ടില്‍ സമ്പര്‍ക്ക വിലക്കില്‍ ഇരിക്കുന്ന വ്യക്തിയെ പറ്റി / Quarantined person in the house",
              "title": "",
              "description": [],
              "nextQues":7,
              "correctAnswer": true
            }
          ]
        },
    		{
          "title": "രോഗ ലക്ഷണങ്ങള്‍",
          "qno":6,
          "description": "add description for question",
          "hint": "",
          "answers": [
            {
              "option": "പനി / Fever",
              "title": "",
              "description": [],
              "nextQues":10,
              "correctAnswer": true
            },
            {
              "option": "ജലദോഷം / Cold",
              "title": "",
              "description": [],
              "nextQues":10,
              "correctAnswer": true
            },
            {
              "option": "മറ്റ് രോഗങ്ങള്‍ / Co-morbidities",
              "title": "",
              "description": [],
              "nextQues":10,
              "correctAnswer": true
            }
          ]
        },
        {
          "title": "ഏത് ജില്ലയില്‍ ആണ് താമസിക്കുന്നത് ",
          "qno":7,
          "description": "add description for question",
          "hint": "",
          "answers": [
            {
              "option": "District",
              "title": "",
              "description": [],
              "nextQues":11,
              "correctAnswer": true
            }
          ]
        },
        {
          "title": "തദ്ദേശ സ്വയംഭരണ സ്ഥാപനം",
          "qno":8,
          "description": "add description for question",
          "hint": "",
          "answers": [
            {
              "option": "ഗ്രാമപഞ്ചായത്ത് / Panchayat",
              "title": "",
              "description": [],
              "nextQues":12,
              "correctAnswer": true
        		},
            {
              "option": "മുനിസിപ്പാലിറ്റി / Municipality",
              "title": "",
              "description": [],
              "nextQues":13,
              "correctAnswer": true
            }
          ]
        },
        {
          "title": "ഗ്രാമപഞ്ചായത്ത് / Panchayat",
          "qno":9,
          "description": "add description for question",
          "hint": "",
          "answers": [
            {
              "option": "PANCHAYAT",
              "title": "",
              "description": [],
              "nextQues":16,
              "correctAnswer": true
        		}
          ]
        },
        {
          "title": "മുനിസിപ്പാലിറ്റി / Municipality",
          "qno":10,
          "description": "add description for question",
          "hint": "",
          "answers": [
            {
              "option": "Municipality",
              "title": "",
              "description": [],
              "nextQues":16,
              "correctAnswer": true
        		}
          ]
        },
        {
          "title": "വാര്‍ഡ്‌ നമ്പര്‍",
          "qno":11,
          "description": "add description for question",
          "hint": "",
          "mode": "text",
          "nextQues":17,
          "answers": []
        },
        {
          "title": "വിലാസം ",
          "qno":12,
          "description": "add description for question",
          "hint": "",
          "mode": "text",
          "nextQues":18,
          "answers": []
        },
        {
          "title": "പിന്‍കോഡ്",
          "qno":13,
          "description": "add description for question",
          "hint": "",
          "mode": "text",
          "nextQues":19,
          "answers": []
        },
        {
          "title": "അടുത്തുള്ള സർക്കാർ ആരോഗ്യ കേന്ദ്രം",
          "qno":14,
          "description": "add description for question",
          "hint": "",
          "mode": "text",
          "nextQues":20,
          "answers": []
        },
        {
          "title": "തിരികെ ഏത് മാര്‍ഗത്തിലൂടെ ബന്ധപ്പെടാനാണ് നിങ്ങള്‍ താല്‍പര്യപ്പെടുന്നത്",
          "qno":15,
          "description": "add description for question",
          "hint": "",
          "answers": [
            {
              "option": "Email",
              "title": "",
              "description": [],
              "nextQues":21,
              "correctAnswer": true
        		},
            {
              "option": "Phone",
              "title": "",
              "description": [],
              "nextQues":22,
              "correctAnswer": true
            },
            {
              "option": "WhatsApp",
              "title": "",
              "description": [],
              "nextQues":22,
              "correctAnswer": true
            }
          ]
        },
        {
          "title": "ഇമെയിൽ",
          "qno":16,
          "description": "add description for question",
          "hint": "",
          "mode": "text",
          "nextQues":-1,
          "answers": []
        }
      ]
    },
    {
      "language": "malayalam",
      "title": "വിദേശയാത്ര ചെയ്തിട്ടുണ്ടോ? അവരുമായി സമ്പർക്കമുണ്ടോ?",
      "description": "താങ്കൾ അടുത്തിടെ വിദേശയാത്ര നടത്തിയ വ്യക്തിയോ അങ്ങനെയുള്ളവരെ അറിയുന്ന ആളോ ആണോ? എങ്കിൽ താഴെയുള്ള ബട്ടൺ അമർത്തി രജിസ്റ്റർ ചെയ്യുക",
      "path": "citizen_foreign_ml",
      "buttonText": "രജിസ്റ്റർ ചെയ്യുക",
      "successMessage": "നന്ദി. Thank You.",
      "readMore": "/",
      "questions": [
        {
          "title": "അന്താരാഷ്ട്ര സഞ്ചാരിയായ ആരുടെ വിവരമാണ് നല്‍കുന്നത്  ?",
          "qno":0,
          "description": "add description for question",
          "hint": "",
          "answers": [
            {
              "option": "സ്വയം / Yourself",
              "title": "",
              "description": [],
              "nextQues":1,
              "correctAnswer": true
            },
            {
              "option": "മറ്റൊരാളെ പറ്റി / Someone elseല",
              "title": "",
              "description": [],
              "nextQues":2,
              "correctAnswer": true
            }
          ]
        },
        {
          "title": "റിപ്പോര്‍ട്ട്‌ ചെയുന്ന വ്യക്തിയുടെ പേര്",
          "qno":1,
          "description": "add description for question",
          "hint": "",
          "mode": "text",
          "nextQues":3,
          "answers": []
        },
        {
          "title": "വിവരം നല്‍കുന്ന വ്യക്തിയുടെ പേര്",
          "qno":2,
          "description": "add description for question",
          "hint": "",
          "mode": "text",
          "nextQues":3,
          "answers": []
        },
        {
          "title": "വിവരം നല്‍കാന്‍ ഉദ്ദേശിക്കുന്ന വ്യക്തിയുടെ പേര് ",
          "qno":3,
          "description": "add description for question",
          "hint": "",
          "mode": "text",
          "nextQues":4,
          "answers": []
        },
        {
          "title": "എന്നാണ് ഇന്ത്യയില്‍ എത്തിയത്",
          "qno":4,
          "description": "add description for question",
          "hint": "",
          "mode": "date",
          "nextQues":5,
          "answers": []
        },
        {
          "title": "ഏത് രാജ്യത്ത് നിന്നാണ് എത്തിയത്",
          "qno":5,
          "description": "add description for question",
          "hint": "",
          "answers": [
            {
              "option": "country",
              "title": "",
              "description": [],
              "nextQues":6,
              "correctAnswer": true
        		}
          ]
        },
        {
          "title": "യാത്ര ചെയ്ത വിമാനത്തിന്‍റെ നമ്പര്‍ ",
          "qno":6,
          "description": "add description for question",
          "hint": "",
          "mode": "text",
          "nextQues":7,
          "answers": []
        },
        {
          "title": "റിപ്പോര്‍ട്ട്‌ ചെയ്യപ്പെട്ട വ്യക്തിയും നിങ്ങളും തമ്മിലുള്ള ബന്ധം ",
          "qno":7,
          "description": "add description for question",
          "hint": "",
          "mode": "text",
          "nextQues":8,
          "answers": []
        },
        {
          "title": "റിപ്പോര്‍ട്ട് ചെയ്യപ്പെട്ട വ്യക്തിയെ ബന്ധപെടാനുള്ള ഫോണ്‍ നമ്പര്‍",
          "qno":8,
          "description": "add description for question",
          "hint": "",
          "mode": "text",
          "nextQues":9,
          "answers": []
        },
        {
          "title": "ഈ വ്യക്തി സമ്പര്‍ക നിയന്ത്രണത്തിലോ/ സമ്പര്‍ക വിലക്കിലോ ആണോ ? ",
          "qno":9,
          "description": "add description for question",
          "hint": "",
          "answers": [
            {
              "option": "ഉണ്ട് / Yes",
              "title": "",
              "description": [],
              "nextQues":10,
              "correctAnswer": true
        		},
            {
              "option": "ഇല്ല / No",
              "title": "",
              "description": [],
              "nextQues":10,
              "correctAnswer": true
        		}
          ]
        },
        {
          "title": "റിപ്പോർട്ട് ചെയ്യപ്പെടുന്ന വ്യക്തി ",
          "qno":10,
          "description": "add description for question",
          "hint": "",
          "answers": [
            {
              "option": "60 വയസ്സിനു മുകളിൽ",
              "title": "",
              "description": [],
              "nextQues":12,
              "correctAnswer": true
        		},
            {
              "option": "ഇതൊന്നുമല്ല",
              "title": "",
              "description": [],
              "nextQues":12,
              "correctAnswer": true
        		},
            {
              "option": "മറ്റ് രോഗങ്ങള്‍",
              "title": "",
              "description": [],
              "nextQues":11,
              "correctAnswer": true
        		}
          ]
        },
        {
          "title": "മറ്റ് രോഗങ്ങള്‍ ",
          "qno":11,
          "description": "add description for question",
          "hint": "",
          "answers": [
            {
              "option": "പ്രമേഹം",
              "title": "",
              "description": [],
              "nextQues":11,
              "correctAnswer": true
        		},
            {
              "option": "രക്താദിമര്‍ദ്ദം",
              "title": "",
              "description": [],
              "nextQues":11,
              "correctAnswer": true
        		},
            {
              "option": "സ്ട്രോക്ക്",
              "title": "",
              "description": [],
              "nextQues":11,
              "correctAnswer": true
        		},
            {
              "option": "അര്‍ബുദംക്",
              "title": "",
              "description": [],
              "nextQues":11,
              "correctAnswer": true
        		},
            {
              "option": "ശ്വാസകോശ രോഗങ്ങള്‍",
              "title": "",
              "description": [],
              "nextQues":11,
              "correctAnswer": true
        		},
            {
              "option": "വൃക്ക- കരള്‍ രോഗം",
              "title": "",
              "description": [],
              "nextQues":11,
              "correctAnswer": true
        		},
            {
              "option": "കിടപ്പ് രോഗികള്‍",
              "title": "",
              "description": [],
              "nextQues":11,
              "correctAnswer": true
        		},
            {
              "option": "ഹൃദ്രോഗം",
              "title": "",
              "description": [],
              "nextQues":11,
              "correctAnswer": true
        		}
          ]
        },
        {
          "title": "ഏത് ജില്ലയില്‍ ആണ് താമസിക്കുന്നത് ",
          "qno":12,
          "description": "add description for question",
          "hint": "",
          "answers": [
            {
              "option": "District",
              "title": "",
              "description": [],
              "nextQues":12,
              "correctAnswer": true
            }
          ]
        },
        {
          "title": "തദ്ദേശ സ്വയംഭരണ സ്ഥാപനം",
          "qno":13,
          "description": "add description for question",
          "hint": "",
          "answers": [
            {
              "option": "ഗ്രാമപഞ്ചായത്ത് / Panchayat",
              "title": "",
              "description": [],
              "nextQues":13,
              "correctAnswer": true
        		},
            {
              "option": "മുനിസിപ്പാലിറ്റി / Municipality",
              "title": "",
              "description": [],
              "nextQues":14,
              "correctAnswer": true
            }
          ]
        },
        {
          "title": "ഗ്രാമപഞ്ചായത്ത് / Panchayat",
          "qno":14,
          "description": "add description for question",
          "hint": "",
          "answers": [
            {
              "option": "PANCHAYAT",
              "title": "",
              "description": [],
              "nextQues":17,
              "correctAnswer": true
        		}
          ]
        },
        {
          "title": "മുനിസിപ്പാലിറ്റി / Municipality",
          "qno":15,
          "description": "add description for question",
          "hint": "",
          "answers": [
            {
              "option": "Municipality",
              "title": "",
              "description": [],
              "nextQues":17,
              "correctAnswer": true
        		}
          ]
        },
        {
          "title": "വാര്‍ഡ്‌ നമ്പര്‍",
          "qno":16,
          "description": "add description for question",
          "hint": "",
          "mode": "text",
          "nextQues":18,
          "answers": []
        },
        {
          "title": "വിലാസം",
          "qno":17,
          "description": "add description for question",
          "hint": "",
          "mode": "text",
          "nextQues":19,
          "answers": []
        },
        {
          "title": "പിന്‍കോഡ്",
          "qno":18,
          "description": "add description for question",
          "hint": "",
          "mode": "text",
          "nextQues":20,
          "answers": []
        },
        {
          "title": "ജില്ലാ ആരോഗ്യ കേന്ദ്രംദ്രം",
          "qno":19,
          "description": "add description for question",
          "hint": "",
          "mode": "text",
          "nextQues":21,
          "answers": []
        },
        {
          "title": "തിരികെ ഏത് മാര്‍ഗത്തിലൂടെ ബന്ധപ്പെടാനാണ് നിങ്ങള്‍ താല്‍പര്യപ്പെടുന്നത്",
          "qno":20,
          "description": "add description for question",
          "hint": "",
          "answers": [
            {
              "option": "Email",
              "title": "",
              "description": [],
              "nextQues":22,
              "correctAnswer": true
        		},
            {
              "option": "Phone",
              "title": "",
              "description": [],
              "nextQues":23,
              "correctAnswer": true
            },
            {
              "option": "WhatsApp",
              "title": "",
              "description": [],
              "nextQues":23,
              "correctAnswer": true
            }
          ]
        },
        {
          "title": "ഇമെയിൽ",
          "qno":21,
          "description": "add description for question",
          "hint": "",
          "mode": "text",
          "nextQues":23,
          "answers": []
        },
        {
          "title": "Terms and Conditions",
          "description": "add description for question",
          "hint": "",
          "answers": [
            {
              "option": "By submitting this survey, you agree to the Terms and conditions on how your data will be handled",
              "title": "",
              "description": [],
        		}
          ]
        }
      ]
    },
    {
      "language": "malayalam",
      "title": "ഇന്ത്യയിൽ എവിടെയെങ്കിലും യാത്ര ചെയ്തിട്ടുണ്ടോ? അവരുമായി സമ്പർക്കമുണ്ടോ?",
      "description": "താങ്കൾ അടുത്തിടെ ഇന്ത്യയിൽ എവിടെയെങ്കിലും യാത്ര നടത്തിയ വ്യക്തിയോ അങ്ങനെയുള്ളവരെ അറിയുന്ന ആളോ ആണോ? എങ്കിൽ താഴെയുള്ള ബട്ടൺ അമർത്തി രജിസ്റ്റർ ചെയ്യുക",
      "path": "citizen_state_ml",
      "buttonText": "രജിസ്റ്റർ ചെയ്യുക",
      "successMessage": "നന്ദി. Thank You.",
      "readMore": "/",
      "questions": [
        {
          "title": "അന്തര്‍ സംസ്ഥാന  സഞ്ചാരിയായ ആരുടെ വിവരമാണ് നല്‍കുന്നത് ?",
          "description": "add description for question",
          "hint": "",
          "answers": [
            {
              "option": "സ്വയം / Yourself",
              "title": "",
              "description": [],
              "nextQues":2,
              "correctAnswer": true
            },
            {
              "option": "മറ്റൊരാളെ പറ്റി / Someone elseല",
              "title": "",
              "description": [],
              "nextQues":23,
              "correctAnswer": true
            }
          ]
        },
        {
          "title": "റിപ്പോര്‍ട്ട്‌ ചെയുന്ന വ്യക്തിയുടെ പേര്",
          "description": "add description for question",
          "hint": "",
          "mode": "text",
          "nextQues":3,
          "answers": []
        },
        {
          "title": "എന്നാണ് കേരളത്തില്‍ എത്തിയത്",
          "description": "add description for question",
          "hint": "",
          "mode": "date",
          "nextQues":4,
          "answers": []
        },
        {
          "title": "ഏത് സംസ്ഥാനത്ത്  നിന്നാണ് എത്തിയത്",
          "description": "add description for question",
          "hint": "",
          "mode": "text",
          "nextQues":5,
          "answers": []
        },
        {
          "title": "ഏത് മാര്‍ഗത്തിലൂടെ ആണ് കേരളത്തില്‍ എത്തിയത്",
          "description": "add description for question",
          "hint": "",
          "mode": "text",
          "nextQues":6,
          "answers": [
            {
              "option": "ട്രെയിൻ / Train",
              "title": "",
              "description": [],
              "nextQues":6,
              "correctAnswer": true
            },
            {
              "option": "ബസ് / Bus",
              "title": "",
              "description": [],
              "nextQues":6,
              "correctAnswer": true
            },
            {
              "option": "വിമാനം / Airplane",
              "title": "",
              "description": [],
              "nextQues":6,
              "correctAnswer": true
            },
            {
              "option": "കാര് / Car",
              "title": "",
              "description": [],
              "nextQues":6,
              "correctAnswer": true
            },
            {
              "option": "ടാക്സി / Taxi",
              "title": "",
              "description": [],
              "nextQues":6,
              "correctAnswer": true
            },
            {
              "option": "മറ്റുള്ളവ / Other",
              "title": "",
              "description": [],
              "nextQues":6,
              "correctAnswer": true
            }
          ]
        },
        {
           "title": "Please specify",
           "description": "add description for question",
           "hint": "",
           "mode": "text",
           "nextQues":6,
           "answers": []
        },
        {
          "title": "നിങ്ങള്‍ സമ്പര്‍ക നിയന്ത്രണത്തിലോ/ സമ്പര്‍ക വിലക്കിലോ ആണോ ?",
          "description": "add description for question",
          "hint": "",
          "mode": "date",
          "nextQues":7,
          "answers": [{
              "option": "ഉണ്ട് / Yes",
              "title": "",
              "description": [],
              "nextQues":7,
              "correctAnswer": true
            },
            {
              "option": "ഇല്ല / No",
              "title": "",
              "description": [],
              "nextQues":7,
              "correctAnswer": true
            }
          ]
        },
        {
          "title": "റിപ്പോർട്ട് ചെയ്യപ്പെടുന്ന വ്യക്തി",
          "description": "add description for question",
          "hint": "",
          "mode": "text",
          "nextQues":7,
          "answers": [{
              "option": "60 വയസ്സിനു മുകളിൽ",
              "title": "",
              "description": [],
              "nextQues":9,
              "correctAnswer": true
            },
            {
              "option": "മറ്റ് രോഗങ്ങള്‍",
              "title": "",
              "description": [],
              "nextQues":8,
              "correctAnswer": true
            },
            {
              "option": "ഇതൊന്നുമല്ല",
              "title": "",
              "description": [],
              "nextQues":9,
              "correctAnswer": true
            }
          ]
        },
        {
          "title": "ഏത് ജില്ലയില്‍ ആണ് താമസിക്കുന്നത്",
          "description": "add description for question",
          "hint": "",
          "mode": "text",
          "nextQues":10,
          "answers": [
          {
              "option": "District",
              "title": "",
              "description": [],
              "nextQues":10,
              "correctAnswer": true
            }
          ]
        },
        {
          "title": "തദ്ദേശ സ്വയംഭരണ സ്ഥാപനം ?",
          "description": "add description for question",
          "hint": "",
          "mode": "date",
          "nextQues":10,
          "answers": [
            {
              "option": "ഗ്രാമപഞ്ചായത്ത് / Panchayat",
              "title": "",
              "description": [],
              "nextQues":11,
              "correctAnswer": true
            },
            {
              "option": "മുനിസിപ്പാലിറ്റി / Municipality",
              "title": "",
              "description": [],
              "nextQues":12,
              "correctAnswer": true
            }
          ]
        },
        {
          "title": "ഗ്രാമപഞ്ചായത്ത് / Panchayat",
          "description": "add description for question",
          "hint": "",
          "mode": "Aalakode options",
          "nextQues":15,
          "answers": []
        },
        {
          "title": "വാര്‍ഡ്‌ നമ്പര്‍",
          "description": "add description for question",
          "hint": "",
          "mode": "ward number options",
          "nextQues":16,
          "answers": []
        },
        {
          "title": "വിലാസം",
          "description": "add description for question",
          "hint": "",
          "mode": "address",
          "nextQues":17,
          "answers": []
        },
        {
          "title": "പിന്‍കോഡ്",
          "description": "add description for question",
          "hint": "",
          "mode": "pin code",
          "nextQues":19,
          "answers": []
        },
        {
          "title": "താഴെ പറയുന്ന രോഗലക്ഷണം നിങ്ങള്‍ക്ക് ഉണ്ടോ? ",
          "description": "add description for question",
          "hint": "",
          "mode": "option",
          "nextQues":20,
          "answers": [
            {
              "option": "പനി / Fever",
              "title": "",
              "description": [],
              "nextQues":20,
              "correctAnswer": true
            },
            {
              "option": "ചുമ / Cough",
              "title": "",
              "description": [],
              "nextQues":20,
              "correctAnswer": true
            },
            {
              "option": "ശ്വാസ തടസ്സം / Running nose",
              "title": "",
              "description": [],
              "nextQues":1,
              "correctAnswer": true
            },
            {
              "option": "ശ്വാസംമുട്ട് / Shortness of breath",
              "title": "",
              "description": [],
              "nextQues":20,
              "correctAnswer": true
            },
            {
              "option": "തൊണ്ടവേദന / Sore throat",
              "title": "",
              "description": [],
              "nextQues":20,
              "correctAnswer": true
            },
            {
              "option": "Others",
              "title": "",
              "description": [],
              "nextQues":21,
              "correctAnswer": true
            }
          ]
        },
        {
          "title": "Any other symptoms?",
          "description": "add description for question",
          "hint": "",
          "mode": "text",
          "nextQues":20,
          "answers": []
        },
        {
          "title": "തിരികെ ഏത് മാര്‍ഗത്തിലൂടെ ബന്ധപ്പെടാനാണ് നിങ്ങള്‍ താല്‍പര്യപ്പെടുന്നത് ",
          "description": "add description for question",
          "hint": "",
          "mode": "pin code",
          "nextQues":21,
          "answers": [
            {
              "option": "Email",
              "title": "",
              "description": [],
              "nextQues":21,
              "correctAnswer": true
            },
            {
              "option": "Phone",
              "title": "",
              "description": [],
              "nextQues":-1,
              "correctAnswer": true
            },
            {
              "option": "Whatsapp",
              "title": "",
              "description": [],
              "nextQues":-1,
              "correctAnswer": true
            }
          ]
        },
        {
          "title": "Email",
          "description": "add description for question",
          "hint": "",
          "mode": "text",
          "nextQues":22,
          "answers": []
        },
        {
          "title": "Please specify",
          "description": "add description for question",
          "hint": "",
          "mode": "text",
          "nextQues":6,
          "answers": []
        },
        {
          "title": "മറ്റ് രോഗങ്ങള്‍ ",
          "description": "add description for question",
          "hint": "",
          "mode": "text",
          "nextQues":7,
          "answers": [
            {
              "option": "പ്രമേഹം",
              "title": "",
              "description": [],
              "nextQues":9,
              "correctAnswer": true
            },
            {
              "option": "രക്താദിമര്‍ദ്ദം",
              "title": "",
              "description": [],
              "nextQues":9,
              "correctAnswer": true
            },
            {
              "option": "സ്ട്രോക്ക്ല",
              "title": "",
              "description": [],
              "nextQues":9,
              "correctAnswer": true
            },
            {
              "option": "അര്‍ബുദം",
              "title": "",
              "description": [],
              "nextQues":9,
              "correctAnswer": true
            },
            {
              "option": "ശ്വാസകോശ രോഗങ്ങള്‍ക്ല",
              "title": "",
              "description": [],
              "nextQues":9,
              "correctAnswer": true
            },
            {
              "option": "വൃക്ക- കരള്‍ രോഗംക്ല",
              "title": "",
              "description": [],
              "nextQues":9,
              "correctAnswer": true
            },
            {
              "option": "കിടപ്പ് രോഗികള്‍",
              "title": "",
              "description": [],
              "nextQues":9,
              "correctAnswer": true
            },
            {
              "option": "ഹൃദ്രോഗം",
              "title": "",
              "description": [],
              "nextQues":9,
              "correctAnswer": true
            }
          ]
        },
        {
          "title": "വിവരം നല്‍കുന്ന വ്യക്തിയുടെ പേര്",
          "description": "add description for question",
          "hint": "",
          "mode": "text",
          "nextQues":3,
          "answers": []
        },
        {
          "title": "വിവരം നല്‍കാന്‍ ഉദ്ദേശിക്കുന്ന വ്യക്തിയുടെ പേര്",
          "description": "add description for question",
          "hint": "",
          "mode": "text",
          "nextQues":4,
          "answers": []
        },
        {
          "title": "എന്നാണ് കേരളത്തില്‍ എത്തിയത്",
          "description": "add description for question",
          "hint": "",
          "mode": "date",
          "nextQues":25,
          "answers": []
        },
        {
          "title": "ഏത് സംസ്ഥാനത്ത്  നിന്നാണ് എത്തിയത്",
          "description": "add description for question",
          "hint": "",
          "mode": "State options",
          "nextQues":26,
          "answers": []
        },
        {
          "title": "റിപ്പോര്‍ട്ട്‌ ചെയ്യപ്പെട്ട വ്യക്തിയും നിങ്ങളും തമ്മിലുള്ള ബന്ധം",
          "description": "add description for question",
          "hint": "",
          "mode": "text",
          "nextQues":27,
          "answers": []
        },
        {
          "title": "റിപ്പോര്‍ട്ട് ചെയ്യപ്പെട്ട വ്യക്തിയെ ബന്ധപെടാനുള്ള ഫോണ്‍ നമ്പര്‍ധം",
          "description": "add description for question",
          "hint": "",
          "mode": "Phone number",
          "nextQues":6,
          "answers": []
        },
        {
          "title": "നിങ്ങള്‍ സമ്പര്‍ക നിയന്ത്രണത്തിലോ/ സമ്പര്‍ക വിലക്കിലോ ആണോ ?",
          "description": "add description for question",
          "hint": "",
          "mode": "Phone number",
          "nextQues":27,
          "answers": [{
              "option": "ഉണ്ട് / Yes",
              "title": "",
              "description": [],
              "nextQues":9,
              "correctAnswer": true
            },
            {
              "option": "ഇല്ല / No",
              "title": "",
              "description": [],
              "nextQues":9,
              "correctAnswer": true
            }
          ]
        }
      ]
    }
  ],
  "links": []
}
